MANIFEST.in
Makefile
README
setup.py
test/__init__.py
test/__init__.pyc
test/setup_test.py
test/setup_test.pyc
tiddlywebplugins/__init__.py
tiddlywebplugins/kml.py
tiddlywebplugins.kml.egg-info/PKG-INFO
tiddlywebplugins.kml.egg-info/SOURCES.txt
tiddlywebplugins.kml.egg-info/dependency_links.txt
tiddlywebplugins.kml.egg-info/namespace_packages.txt
tiddlywebplugins.kml.egg-info/not-zip-safe
tiddlywebplugins.kml.egg-info/requires.txt
tiddlywebplugins.kml.egg-info/top_level.txt