Metadata-Version: 1.0
Name: tiddlywebplugins.kml
Version: 0.2.2
Summary: Adds support for KML files
Home-page: http://pypi.python.org/pypi/tiddlywebplugins.kml
Author: Ben Gillies
Author-email: bengillies@gmail.com
License: UNKNOWN
Platform: Posix; MacOS X; Windows
